<?xml version="1.0" encoding="UTF-8"?>
<export version="E">
  <design>
    <source>/Users/adrian/git/ESP32-Daikin/KiCad/Daikin.kicad_sch</source>
    <date>Sunday, 03 April 2022 at 14:45:45</date>
    <tool>Eeschema (6.0.2-0)</tool>
    <textvar name="DATE">2022-04-02</textvar>
    <sheet number="1" name="/" tstamps="/">
      <title_block>
        <title>Daikin ESP32-PICO-MINI module</title>
        <company/>
        <rev>1</rev>
        <date>2022-04-02</date>
        <source>Daikin.kicad_sch</source>
        <comment number="1" value="@TheRealRevK"/>
        <comment number="2" value="www.me.uk"/>
        <comment number="3" value=""/>
        <comment number="4" value=""/>
        <comment number="5" value=""/>
        <comment number="6" value=""/>
        <comment number="7" value=""/>
        <comment number="8" value=""/>
        <comment number="9" value=""/>
      </title_block>
    </sheet>
  </design>
  <components>
    <comp ref="C1">
      <value>10nF</value>
      <footprint>RevK:C_0603</footprint>
      <libsource lib="Device" part="C" description="Unpolarized capacitor"/>
      <property name="Sheetname" value=""/>
      <property name="Sheetfile" value="Daikin.kicad_sch"/>
      <sheetpath names="/" tstamps="/"/>
      <tstamps>aea0762f-9b4b-49c8-b311-2b433e5a47c4</tstamps>
    </comp>
    <comp ref="C2">
      <value>0.1uF</value>
      <footprint>RevK:Hidden</footprint>
      <fields>
        <field name="Note">X7R or X5R 0603</field>
      </fields>
      <libsource lib="RevK" part="Hidden" description=""/>
      <property name="Note" value="X7R or X5R 0603"/>
      <property name="Part No" value=""/>
      <property name="Sheetname" value=""/>
      <property name="Sheetfile" value="Daikin.kicad_sch"/>
      <sheetpath names="/" tstamps="/"/>
      <tstamps>00000000-0000-0000-0000-0000610f9b88</tstamps>
    </comp>
    <comp ref="C3">
      <value>2.2uF</value>
      <footprint>RevK:Hidden</footprint>
      <fields>
        <field name="Note">0603 or 0805</field>
      </fields>
      <libsource lib="RevK" part="Hidden" description=""/>
      <property name="Note" value="0603 or 0805"/>
      <property name="Part No" value=""/>
      <property name="Sheetname" value=""/>
      <property name="Sheetfile" value="Daikin.kicad_sch"/>
      <sheetpath names="/" tstamps="/"/>
      <tstamps>00000000-0000-0000-0000-0000610fd0ef</tstamps>
    </comp>
    <comp ref="C4">
      <value>10uF</value>
      <footprint>RevK:Hidden</footprint>
      <fields>
        <field name="Note">0603 or 0805</field>
      </fields>
      <libsource lib="RevK" part="Hidden" description=""/>
      <property name="Note" value="0603 or 0805"/>
      <property name="Part No" value=""/>
      <property name="Sheetname" value=""/>
      <property name="Sheetfile" value="Daikin.kicad_sch"/>
      <sheetpath names="/" tstamps="/"/>
      <tstamps>00000000-0000-0000-0000-0000610fd80e</tstamps>
    </comp>
    <comp ref="C5">
      <value>100nF</value>
      <footprint>RevK:C_0603</footprint>
      <libsource lib="Device" part="C" description="Unpolarized capacitor"/>
      <property name="Sheetname" value=""/>
      <property name="Sheetfile" value="Daikin.kicad_sch"/>
      <sheetpath names="/" tstamps="/"/>
      <tstamps>296b967f-b7a9-453f-856a-7b874fdca3db</tstamps>
    </comp>
    <comp ref="D1">
      <value>RGB</value>
      <footprint>RevK:LED-RGB-1.6x1.6</footprint>
      <fields>
        <field name="Manufacturer">Kingbright</field>
        <field name="Part No">APTF1616LSEEZGKQBKC</field>
      </fields>
      <libsource lib="Device" part="LED_ARGB" description="RGB LED, anode/red/green/blue"/>
      <property name="Manufacturer" value="Kingbright"/>
      <property name="Part No" value="APTF1616LSEEZGKQBKC"/>
      <property name="Sheetname" value=""/>
      <property name="Sheetfile" value="Daikin.kicad_sch"/>
      <sheetpath names="/" tstamps="/"/>
      <tstamps>c402b2b8-0bbd-4038-b1b9-845d84949881</tstamps>
    </comp>
    <comp ref="D2">
      <value>Schottky</value>
      <footprint>RevK:Hidden</footprint>
      <datasheet>https://www.mouser.co.uk/datasheet/2/54/CD1206-B220_B2100-777245.pdf</datasheet>
      <fields>
        <field name="Manufacturer">Bourns</field>
        <field name="Part No">CD1206-B2100</field>
      </fields>
      <libsource lib="RevK" part="Hidden" description=""/>
      <property name="Manufacturer" value="Bourns"/>
      <property name="Part No" value="CD1206-B2100"/>
      <property name="Note" value=""/>
      <property name="Sheetname" value=""/>
      <property name="Sheetfile" value="Daikin.kicad_sch"/>
      <sheetpath names="/" tstamps="/"/>
      <tstamps>00000000-0000-0000-0000-0000610fe5d2</tstamps>
    </comp>
    <comp ref="J1">
      <value>SPOX</value>
      <footprint>RevK:Molex_MiniSPOX_H4RA</footprint>
      <libsource lib="Connector_Generic" part="Conn_01x04" description="Generic connector, single row, 01x04, script generated (kicad-library-utils/schlib/autogen/connector/)"/>
      <property name="Sheetname" value=""/>
      <property name="Sheetfile" value="Daikin.kicad_sch"/>
      <sheetpath names="/" tstamps="/"/>
      <tstamps>af073fa6-a783-40f2-9751-692984a62ffc</tstamps>
    </comp>
    <comp ref="L1">
      <value>6.8uH</value>
      <footprint>RevK:Hidden</footprint>
      <datasheet>https://www.mouser.co.uk/datasheet/2/987/Laird_Performance_TYA4020_series__Rev_A_-1877538.pdf</datasheet>
      <fields>
        <field name="Manufacturer">Laird</field>
        <field name="Part No">TYA4020</field>
      </fields>
      <libsource lib="RevK" part="Hidden" description=""/>
      <property name="Manufacturer" value="Laird"/>
      <property name="Part No" value="TYA4020"/>
      <property name="Note" value=""/>
      <property name="Sheetname" value=""/>
      <property name="Sheetfile" value="Daikin.kicad_sch"/>
      <sheetpath names="/" tstamps="/"/>
      <tstamps>00000000-0000-0000-0000-0000610fe01a</tstamps>
    </comp>
    <comp ref="Q3">
      <value>PMF250XNEX</value>
      <footprint>Package_TO_SOT_SMD:SOT-323_SC-70</footprint>
      <libsource lib="RevK" part="NX7002AK" description="N-MOSFET transistor, gate/source/drain"/>
      <property name="Sheetname" value=""/>
      <property name="Sheetfile" value="Daikin.kicad_sch"/>
      <sheetpath names="/" tstamps="/"/>
      <tstamps>ebcfdf36-110d-4f79-9de0-e4fcd76c1d6e</tstamps>
    </comp>
    <comp ref="R1">
      <value>680R</value>
      <footprint>RevK:R_0603</footprint>
      <libsource lib="Device" part="R" description="Resistor"/>
      <property name="Sheetname" value=""/>
      <property name="Sheetfile" value="Daikin.kicad_sch"/>
      <sheetpath names="/" tstamps="/"/>
      <tstamps>06b0f59d-5955-4cff-a86d-1a17e2ebba6e</tstamps>
    </comp>
    <comp ref="R2">
      <value>2K</value>
      <footprint>RevK:R_0603</footprint>
      <libsource lib="Device" part="R" description="Resistor"/>
      <property name="Sheetname" value=""/>
      <property name="Sheetfile" value="Daikin.kicad_sch"/>
      <sheetpath names="/" tstamps="/"/>
      <tstamps>79395739-5b58-4aae-aef4-d23a7b2201c1</tstamps>
    </comp>
    <comp ref="R3">
      <value>220R</value>
      <footprint>RevK:R_0603</footprint>
      <libsource lib="Device" part="R" description="Resistor"/>
      <property name="Sheetname" value=""/>
      <property name="Sheetfile" value="Daikin.kicad_sch"/>
      <sheetpath names="/" tstamps="/"/>
      <tstamps>d6338c10-d82f-4d48-a66e-2ce47a2f9a18</tstamps>
    </comp>
    <comp ref="R4">
      <value>10K</value>
      <footprint>RevK:R_0603</footprint>
      <libsource lib="Device" part="R" description="Resistor"/>
      <property name="Sheetname" value=""/>
      <property name="Sheetfile" value="Daikin.kicad_sch"/>
      <sheetpath names="/" tstamps="/"/>
      <tstamps>1f797175-97b5-4fed-b82b-5985f9063700</tstamps>
    </comp>
    <comp ref="R5">
      <value>100k 1% or 0R</value>
      <footprint>RevK:R_0603</footprint>
      <libsource lib="Device" part="R" description="Resistor"/>
      <property name="Sheetname" value=""/>
      <property name="Sheetfile" value="Daikin.kicad_sch"/>
      <sheetpath names="/" tstamps="/"/>
      <tstamps>fc3ca677-79f2-42b6-a5b3-ff3b18df1d6c</tstamps>
    </comp>
    <comp ref="R6">
      <value>30k 1% or NF</value>
      <footprint>RevK:R_0603</footprint>
      <libsource lib="Device" part="R" description="Resistor"/>
      <property name="Sheetname" value=""/>
      <property name="Sheetfile" value="Daikin.kicad_sch"/>
      <sheetpath names="/" tstamps="/"/>
      <tstamps>83151023-5106-4495-aeff-aefc75dfd6c0</tstamps>
    </comp>
    <comp ref="U1">
      <value>ESP32-PICO-MINI-02</value>
      <footprint>RevK:ESP32-PICO-MINI-02</footprint>
      <fields>
        <field name="MANUFACTURER">Espressif</field>
        <field name="MAXIMUM_PACKAGE_HEIGHT">2.55mm</field>
        <field name="PARTREV">v1.0</field>
        <field name="STANDARD">Manufacturer Recommendations</field>
      </fields>
      <libsource lib="RevK" part="ESP32-PICO-MINI-02" description=""/>
      <property name="MANUFACTURER" value="Espressif"/>
      <property name="MAXIMUM_PACKAGE_HEIGHT" value="2.55mm"/>
      <property name="PARTREV" value="v1.0"/>
      <property name="STANDARD" value="Manufacturer Recommendations"/>
      <property name="Sheetname" value=""/>
      <property name="Sheetfile" value="Daikin.kicad_sch"/>
      <sheetpath names="/" tstamps="/"/>
      <tstamps>7943a3d5-b195-4a57-b3e1-ee29355f1eeb</tstamps>
    </comp>
    <comp ref="U2">
      <value>LMR16006+FB</value>
      <footprint>RevK:RegulatorBlockFB</footprint>
      <fields>
        <field name="Manufacturer">TI</field>
        <field name="Part No">LMR16006YQ3</field>
      </fields>
      <libsource lib="RevK" part="LMR16006+FB" description=""/>
      <property name="Manufacturer" value="TI"/>
      <property name="Part No" value="LMR16006YQ3"/>
      <property name="Sheetname" value=""/>
      <property name="Sheetfile" value="Daikin.kicad_sch"/>
      <sheetpath names="/" tstamps="/"/>
      <tstamps>c88f1737-32b5-4cea-a76f-93ad322556d3</tstamps>
    </comp>
  </components>
  <libparts>
    <libpart lib="Connector_Generic" part="Conn_01x04">
      <description>Generic connector, single row, 01x04, script generated (kicad-library-utils/schlib/autogen/connector/)</description>
      <docs>~</docs>
      <footprints>
        <fp>Connector*:*_1x??_*</fp>
      </footprints>
      <fields>
        <field name="Reference">J2</field>
        <field name="Value">SPOX</field>
        <field name="Footprint">RevK:Molex_MiniSPOX_H4RA</field>
        <field name="Datasheet">~</field>
      </fields>
      <pins>
        <pin num="1" name="Pin_1" type="power_out"/>
        <pin num="2" name="Pin_2" type="power_out"/>
        <pin num="3" name="Pin_3" type="passive"/>
        <pin num="4" name="Pin_4" type="passive"/>
      </pins>
    </libpart>
    <libpart lib="Connector_Generic" part="Conn_01x05">
      <description>Generic connector, single row, 01x05, script generated (kicad-library-utils/schlib/autogen/connector/)</description>
      <docs>~</docs>
      <footprints>
        <fp>Connector*:*_1x??_*</fp>
      </footprints>
      <fields>
        <field name="Reference">J2</field>
        <field name="Value">Prog</field>
        <field name="Footprint">Connector_PinHeader_2.54mm:PinHeader_1x05_P2.54mm_Vertical</field>
        <field name="Datasheet">~</field>
      </fields>
      <pins>
        <pin num="1" name="Pin_1" type="power_in"/>
        <pin num="2" name="Pin_2" type="passive"/>
        <pin num="3" name="Pin_3" type="power_in"/>
        <pin num="4" name="Pin_4" type="passive"/>
        <pin num="5" name="Pin_5" type="passive"/>
      </pins>
    </libpart>
    <libpart lib="Device" part="C">
      <description>Unpolarized capacitor</description>
      <docs>~</docs>
      <footprints>
        <fp>C_*</fp>
      </footprints>
      <fields>
        <field name="Reference">C</field>
        <field name="Value">C</field>
        <field name="Datasheet">~</field>
      </fields>
      <pins>
        <pin num="1" name="" type="passive"/>
        <pin num="2" name="" type="passive"/>
      </pins>
    </libpart>
    <libpart lib="Device" part="LED_ARGB">
      <description>RGB LED, anode/red/green/blue</description>
      <docs>~</docs>
      <footprints>
        <fp>LED*</fp>
        <fp>LED_SMD:*</fp>
        <fp>LED_THT:*</fp>
      </footprints>
      <fields>
        <field name="Reference">D</field>
        <field name="Value">LED_ARGB</field>
        <field name="Datasheet">~</field>
      </fields>
      <pins>
        <pin num="1" name="A" type="passive"/>
        <pin num="2" name="RK" type="passive"/>
        <pin num="3" name="GK" type="passive"/>
        <pin num="4" name="BK" type="passive"/>
      </pins>
    </libpart>
    <libpart lib="Device" part="R">
      <description>Resistor</description>
      <docs>~</docs>
      <footprints>
        <fp>R_*</fp>
      </footprints>
      <fields>
        <field name="Reference">R</field>
        <field name="Value">R</field>
        <field name="Datasheet">~</field>
      </fields>
      <pins>
        <pin num="1" name="" type="passive"/>
        <pin num="2" name="" type="passive"/>
      </pins>
    </libpart>
    <libpart lib="RevK" part="ESP32-PICO-MINI-02">
      <fields>
        <field name="Reference">U</field>
        <field name="Value">ESP32-PICO-MINI-02</field>
        <field name="Footprint">RevK:ESP32-PICO-MINI-02</field>
        <field name="MANUFACTURER">Espressif</field>
        <field name="MAXIMUM_PACKAGE_HEIGHT">2.55mm</field>
        <field name="PARTREV">v1.0</field>
        <field name="STANDARD">Manufacturer Recommendations</field>
      </fields>
      <pins>
        <pin num="1" name="GND" type="power_in"/>
        <pin num="2" name="GND" type="power_in"/>
        <pin num="3" name="3V3" type="power_in"/>
        <pin num="4" name="I36" type="input"/>
        <pin num="5" name="I37" type="input"/>
        <pin num="6" name="I38" type="input"/>
        <pin num="7" name="I39" type="input"/>
        <pin num="8" name="EN" type="input"/>
        <pin num="9" name="I34" type="input"/>
        <pin num="10" name="I35" type="input"/>
        <pin num="11" name="GND" type="power_in"/>
        <pin num="12" name="IO32" type="bidirectional"/>
        <pin num="13" name="IO33" type="bidirectional"/>
        <pin num="14" name="GND" type="power_in"/>
        <pin num="15" name="IO25" type="bidirectional"/>
        <pin num="16" name="IO26" type="bidirectional"/>
        <pin num="17" name="IO27" type="bidirectional"/>
        <pin num="18" name="IO14" type="bidirectional"/>
        <pin num="19" name="IO12" type="bidirectional"/>
        <pin num="20" name="IO13" type="bidirectional"/>
        <pin num="21" name="IO15" type="bidirectional"/>
        <pin num="22" name="IO2" type="bidirectional"/>
        <pin num="23" name="IO0" type="bidirectional"/>
        <pin num="24" name="IO4" type="bidirectional"/>
        <pin num="25" name="NC" type="no_connect"/>
        <pin num="26" name="IO20" type="bidirectional"/>
        <pin num="27" name="IO7" type="bidirectional"/>
        <pin num="28" name="IO8" type="bidirectional"/>
        <pin num="29" name="IO5" type="bidirectional"/>
        <pin num="30" name="RXD0" type="bidirectional"/>
        <pin num="31" name="TXD0" type="bidirectional"/>
        <pin num="32" name="NC" type="no_connect"/>
        <pin num="33" name="IO19" type="bidirectional"/>
        <pin num="34" name="IO22" type="bidirectional"/>
        <pin num="35" name="IO21" type="bidirectional"/>
        <pin num="36" name="GND" type="power_in"/>
        <pin num="37" name="GND" type="power_in"/>
        <pin num="38" name="GND" type="power_in"/>
        <pin num="39" name="GND" type="power_in"/>
        <pin num="40" name="GND" type="power_in"/>
        <pin num="41" name="GND" type="power_in"/>
        <pin num="42" name="GND" type="power_in"/>
        <pin num="43" name="GND" type="power_in"/>
        <pin num="44" name="GND" type="power_in"/>
        <pin num="45" name="GND" type="power_in"/>
        <pin num="46" name="GND" type="power_in"/>
        <pin num="47" name="GND" type="power_in"/>
        <pin num="48" name="GND" type="power_in"/>
        <pin num="49" name="GND" type="power_in"/>
        <pin num="50" name="GND" type="power_in"/>
        <pin num="51" name="GND" type="power_in"/>
        <pin num="52" name="GND" type="power_in"/>
        <pin num="53" name="GND" type="power_in"/>
      </pins>
    </libpart>
    <libpart lib="RevK" part="Hidden">
      <fields>
        <field name="Reference">Z</field>
        <field name="Value">Hidden</field>
        <field name="Footprint">RevK:Hidden</field>
      </fields>
      <pins>
        <pin num="~" name="" type="no_connect"/>
      </pins>
    </libpart>
    <libpart lib="RevK" part="LMR16006+FB">
      <fields>
        <field name="Reference">U</field>
        <field name="Value">LMR16006+FB</field>
        <field name="Footprint">RevK:RegulatorBlockFB</field>
        <field name="Manufacturer">TI</field>
        <field name="Part No">LMR16006YQ3</field>
      </fields>
      <pins>
        <pin num="1" name="SHDN" type="input"/>
        <pin num="2" name="VIN" type="power_in"/>
        <pin num="3" name="GND" type="power_in"/>
        <pin num="4" name="VOUT" type="power_out"/>
        <pin num="5" name="FB" type="passive"/>
      </pins>
    </libpart>
    <libpart lib="RevK" part="NX7002AK">
      <description>N-MOSFET transistor, gate/source/drain</description>
      <docs>~</docs>
      <fields>
        <field name="Reference">Q</field>
        <field name="Value">NX7002AK</field>
        <field name="Footprint">Package_TO_SOT_SMD:SOT-23</field>
        <field name="Datasheet">~</field>
      </fields>
      <pins>
        <pin num="1" name="G" type="input"/>
        <pin num="2" name="S" type="passive"/>
        <pin num="3" name="D" type="passive"/>
      </pins>
    </libpart>
  </libparts>
  <libraries>
    <library logical="Connector_Generic">
      <uri>/Applications/KiCad/KiCad.app/Contents/SharedSupport/symbols//Connector_Generic.kicad_sym</uri>
    </library>
    <library logical="Device">
      <uri>/Applications/KiCad/KiCad.app/Contents/SharedSupport/symbols//Device.kicad_sym</uri>
    </library>
    <library logical="RevK">
      <uri>/Users/adrian/Documents/KiCad/6.0/symbols/RevK.kicad_sym</uri>
    </library>
  </libraries>
  <nets>
    <net code="1" name="+3V3">
      <node ref="C5" pin="1" pintype="passive"/>
      <node ref="D1" pin="1" pinfunction="A" pintype="passive"/>
      <node ref="R4" pin="1" pintype="passive"/>
      <node ref="R5" pin="1" pintype="passive"/>
      <node ref="U1" pin="3" pinfunction="3V3" pintype="power_in"/>
      <node ref="U2" pin="4" pinfunction="VOUT" pintype="power_out"/>
    </net>
    <net code="2" name="B">
      <node ref="R3" pin="2" pintype="passive"/>
      <node ref="U1" pin="27" pinfunction="IO7" pintype="bidirectional"/>
    </net>
    <net code="3" name="DC">
      <node ref="J1" pin="2" pinfunction="Pin_2" pintype="power_out"/>
      <node ref="U2" pin="1" pinfunction="SHDN" pintype="input"/>
      <node ref="U2" pin="2" pinfunction="VIN" pintype="power_in"/>
    </net>
    <net code="4" name="EN">
      <node ref="C1" pin="2" pintype="passive"/>
      <node ref="R4" pin="2" pintype="passive"/>
      <node ref="U1" pin="8" pinfunction="EN" pintype="input"/>
    </net>
    <net code="5" name="G">
      <node ref="R2" pin="2" pintype="passive"/>
      <node ref="U1" pin="28" pinfunction="IO8" pintype="bidirectional"/>
    </net>
    <net code="6" name="GND">
      <node ref="C1" pin="1" pintype="passive"/>
      <node ref="C5" pin="2" pintype="passive"/>
      <node ref="J1" pin="1" pinfunction="Pin_1" pintype="power_out"/>
      <node ref="Q3" pin="2" pinfunction="S" pintype="passive"/>
      <node ref="R6" pin="1" pintype="passive"/>
      <node ref="U1" pin="1" pinfunction="GND" pintype="power_in"/>
      <node ref="U1" pin="11" pinfunction="GND" pintype="power_in"/>
      <node ref="U1" pin="14" pinfunction="GND" pintype="power_in"/>
      <node ref="U1" pin="2" pinfunction="GND" pintype="power_in"/>
      <node ref="U1" pin="36" pinfunction="GND" pintype="power_in"/>
      <node ref="U1" pin="37" pinfunction="GND" pintype="power_in"/>
      <node ref="U1" pin="38" pinfunction="GND" pintype="power_in"/>
      <node ref="U1" pin="39" pinfunction="GND" pintype="power_in"/>
      <node ref="U1" pin="40" pinfunction="GND" pintype="power_in"/>
      <node ref="U1" pin="41" pinfunction="GND" pintype="power_in"/>
      <node ref="U1" pin="42" pinfunction="GND" pintype="power_in"/>
      <node ref="U1" pin="43" pinfunction="GND" pintype="power_in"/>
      <node ref="U1" pin="44" pinfunction="GND" pintype="power_in"/>
      <node ref="U1" pin="45" pinfunction="GND" pintype="power_in"/>
      <node ref="U1" pin="46" pinfunction="GND" pintype="power_in"/>
      <node ref="U1" pin="47" pinfunction="GND" pintype="power_in"/>
      <node ref="U1" pin="48" pinfunction="GND" pintype="power_in"/>
      <node ref="U1" pin="49" pinfunction="GND" pintype="power_in"/>
      <node ref="U1" pin="50" pinfunction="GND" pintype="power_in"/>
      <node ref="U1" pin="51" pinfunction="GND" pintype="power_in"/>
      <node ref="U1" pin="52" pinfunction="GND" pintype="power_in"/>
      <node ref="U1" pin="53" pinfunction="GND" pintype="power_in"/>
      <node ref="U2" pin="3" pinfunction="GND" pintype="power_in"/>
    </net>
    <net code="7" name="GPIO0">
      <node ref="U1" pin="23" pinfunction="IO0" pintype="bidirectional"/>
    </net>
    <net code="8" name="I">
      <node ref="U1" pin="30" pinfunction="RXD0" pintype="bidirectional"/>
    </net>
    <net code="9" name="Net-(D1-Pad2)">
      <node ref="D1" pin="2" pinfunction="RK" pintype="passive"/>
      <node ref="R1" pin="1" pintype="passive"/>
    </net>
    <net code="10" name="Net-(D1-Pad3)">
      <node ref="D1" pin="3" pinfunction="GK" pintype="passive"/>
      <node ref="R2" pin="1" pintype="passive"/>
    </net>
    <net code="11" name="Net-(D1-Pad4)">
      <node ref="D1" pin="4" pinfunction="BK" pintype="passive"/>
      <node ref="R3" pin="1" pintype="passive"/>
    </net>
    <net code="12" name="Net-(J1-Pad4)">
      <node ref="J1" pin="4" pinfunction="Pin_4" pintype="passive"/>
      <node ref="Q3" pin="1" pinfunction="G" pintype="input"/>
    </net>
    <net code="13" name="Net-(R5-Pad2)">
      <node ref="R5" pin="2" pintype="passive"/>
      <node ref="R6" pin="2" pintype="passive"/>
      <node ref="U2" pin="5" pinfunction="FB" pintype="passive"/>
    </net>
    <net code="14" name="O">
      <node ref="U1" pin="31" pinfunction="TXD0" pintype="bidirectional"/>
    </net>
    <net code="15" name="R">
      <node ref="R1" pin="2" pintype="passive"/>
      <node ref="U1" pin="33" pinfunction="IO19" pintype="bidirectional"/>
    </net>
    <net code="16" name="RX">
      <node ref="Q3" pin="3" pinfunction="D" pintype="passive"/>
      <node ref="U1" pin="17" pinfunction="IO27" pintype="bidirectional"/>
    </net>
    <net code="17" name="TX">
      <node ref="J1" pin="3" pinfunction="Pin_3" pintype="passive"/>
      <node ref="U1" pin="16" pinfunction="IO26" pintype="bidirectional"/>
    </net>
    <net code="18" name="unconnected-(C2-Pad~)">
      <node ref="C2" pin="" pintype="no_connect"/>
    </net>
    <net code="19" name="unconnected-(C3-Pad~)">
      <node ref="C3" pin="" pintype="no_connect"/>
    </net>
    <net code="20" name="unconnected-(C4-Pad~)">
      <node ref="C4" pin="" pintype="no_connect"/>
    </net>
    <net code="21" name="unconnected-(D2-Pad~)">
      <node ref="D2" pin="" pintype="no_connect"/>
    </net>
    <net code="22" name="unconnected-(L1-Pad~)">
      <node ref="L1" pin="" pintype="no_connect"/>
    </net>
    <net code="23" name="unconnected-(U1-Pad4)">
      <node ref="U1" pin="4" pinfunction="I36" pintype="input+no_connect"/>
    </net>
    <net code="24" name="unconnected-(U1-Pad5)">
      <node ref="U1" pin="5" pinfunction="I37" pintype="input+no_connect"/>
    </net>
    <net code="25" name="unconnected-(U1-Pad6)">
      <node ref="U1" pin="6" pinfunction="I38" pintype="input+no_connect"/>
    </net>
    <net code="26" name="unconnected-(U1-Pad7)">
      <node ref="U1" pin="7" pinfunction="I39" pintype="input+no_connect"/>
    </net>
    <net code="27" name="unconnected-(U1-Pad9)">
      <node ref="U1" pin="9" pinfunction="I34" pintype="input+no_connect"/>
    </net>
    <net code="28" name="unconnected-(U1-Pad10)">
      <node ref="U1" pin="10" pinfunction="I35" pintype="input+no_connect"/>
    </net>
    <net code="29" name="unconnected-(U1-Pad12)">
      <node ref="U1" pin="12" pinfunction="IO32" pintype="bidirectional+no_connect"/>
    </net>
    <net code="30" name="unconnected-(U1-Pad13)">
      <node ref="U1" pin="13" pinfunction="IO33" pintype="bidirectional+no_connect"/>
    </net>
    <net code="31" name="unconnected-(U1-Pad15)">
      <node ref="U1" pin="15" pinfunction="IO25" pintype="bidirectional+no_connect"/>
    </net>
    <net code="32" name="unconnected-(U1-Pad18)">
      <node ref="U1" pin="18" pinfunction="IO14" pintype="bidirectional+no_connect"/>
    </net>
    <net code="33" name="unconnected-(U1-Pad19)">
      <node ref="U1" pin="19" pinfunction="IO12" pintype="bidirectional+no_connect"/>
    </net>
    <net code="34" name="unconnected-(U1-Pad20)">
      <node ref="U1" pin="20" pinfunction="IO13" pintype="bidirectional+no_connect"/>
    </net>
    <net code="35" name="unconnected-(U1-Pad21)">
      <node ref="U1" pin="21" pinfunction="IO15" pintype="bidirectional+no_connect"/>
    </net>
    <net code="36" name="unconnected-(U1-Pad22)">
      <node ref="U1" pin="22" pinfunction="IO2" pintype="bidirectional+no_connect"/>
    </net>
    <net code="37" name="unconnected-(U1-Pad24)">
      <node ref="U1" pin="24" pinfunction="IO4" pintype="bidirectional+no_connect"/>
    </net>
    <net code="38" name="unconnected-(U1-Pad25)">
      <node ref="U1" pin="25" pinfunction="NC" pintype="no_connect"/>
    </net>
    <net code="39" name="unconnected-(U1-Pad26)">
      <node ref="U1" pin="26" pinfunction="IO20" pintype="bidirectional+no_connect"/>
    </net>
    <net code="40" name="unconnected-(U1-Pad29)">
      <node ref="U1" pin="29" pinfunction="IO5" pintype="bidirectional+no_connect"/>
    </net>
    <net code="41" name="unconnected-(U1-Pad32)">
      <node ref="U1" pin="32" pinfunction="NC" pintype="no_connect"/>
    </net>
    <net code="42" name="unconnected-(U1-Pad34)">
      <node ref="U1" pin="34" pinfunction="IO22" pintype="bidirectional+no_connect"/>
    </net>
    <net code="43" name="unconnected-(U1-Pad35)">
      <node ref="U1" pin="35" pinfunction="IO21" pintype="bidirectional+no_connect"/>
    </net>
  </nets>
</export>
